MergeHRISClient/__init__.py
MergeHRISClient/api_client.py
MergeHRISClient/configuration.py
MergeHRISClient/exceptions.py
MergeHRISClient/model_utils.py
MergeHRISClient/rest.py
MergeHRISClient/api/__init__.py
MergeHRISClient/api/account_details_api.py
MergeHRISClient/api/account_token_api.py
MergeHRISClient/api/available_actions_api.py
MergeHRISClient/api/bank_info_api.py
MergeHRISClient/api/benefits_api.py
MergeHRISClient/api/common_model_scopes_api.py
MergeHRISClient/api/companies_api.py
MergeHRISClient/api/delete_account_api.py
MergeHRISClient/api/employee_payroll_runs_api.py
MergeHRISClient/api/employees_api.py
MergeHRISClient/api/employments_api.py
MergeHRISClient/api/force_resync_api.py
MergeHRISClient/api/generate_key_api.py
MergeHRISClient/api/groups_api.py
MergeHRISClient/api/issues_api.py
MergeHRISClient/api/link_token_api.py
MergeHRISClient/api/linked_accounts_api.py
MergeHRISClient/api/locations_api.py
MergeHRISClient/api/passthrough_api.py
MergeHRISClient/api/pay_groups_api.py
MergeHRISClient/api/payroll_runs_api.py
MergeHRISClient/api/regenerate_key_api.py
MergeHRISClient/api/selective_sync_api.py
MergeHRISClient/api/sync_status_api.py
MergeHRISClient/api/teams_api.py
MergeHRISClient/api/time_off_api.py
MergeHRISClient/api/time_off_balances_api.py
MergeHRISClient/api/webhook_receivers_api.py
MergeHRISClient/apis/__init__.py
MergeHRISClient/model/__init__.py
MergeHRISClient/model/account_details.py
MergeHRISClient/model/account_details_and_actions.py
MergeHRISClient/model/account_details_and_actions_integration.py
MergeHRISClient/model/account_details_and_actions_status_enum.py
MergeHRISClient/model/account_integration.py
MergeHRISClient/model/account_token.py
MergeHRISClient/model/account_type_enum.py
MergeHRISClient/model/available_actions.py
MergeHRISClient/model/bank_info.py
MergeHRISClient/model/benefit.py
MergeHRISClient/model/categories_enum.py
MergeHRISClient/model/category_enum.py
MergeHRISClient/model/common_model_scope_data.py
MergeHRISClient-1.4.0.dist-info/LICENSE.md
MergeHRISClient-1.4.0.dist-info/METADATA
MergeHRISClient-1.4.0.dist-info/WHEEL
MergeHRISClient-1.4.0.dist-info/top_level.txt
MergeHRISClient-1.4.0.dist-info/RECORD
