Metadata-Version: 2.1
Name: MergeHRISClient
Version: 1.4.0
Summary: Merge HRIS API
Home-page: 
Author: Merge Team
Author-email: hello@merge.dev
Keywords: OpenAPI,OpenAPI-Generator,Merge HRIS API
Requires-Python: >=3.6
License-File: LICENSE.md
Requires-Dist: urllib3 (>=1.25.3)
Requires-Dist: python-dateutil
